mpipartition/__init__.py
mpipartition/_send_home.py
mpipartition/distribute.py
mpipartition/exchange.py
mpipartition/overload.py
mpipartition/partition.py
mpipartition/scripts/s2_prediction.py
mpipartition/spherical_partition/__init__.py
mpipartition/spherical_partition/s2_distribute.py
mpipartition/spherical_partition/s2_overload.py
mpipartition/spherical_partition/s2_partition.py
mpipartition-1.5.0.dist-info/LICENSE
mpipartition-1.5.0.dist-info/METADATA
mpipartition-1.5.0.dist-info/WHEEL
mpipartition-1.5.0.dist-info/entry_points.txt
mpipartition-1.5.0.dist-info/RECORD
