Metadata-Version: 2.3
Name: mpipartition
Version: 1.5.0
Summary: MPI volume decomposition and particle distribution tools
License: MIT
Keywords: MPI,mpi4py,scientific computing,parallel computing
Author: Michael Buehlmann
Author-email: buehlmann.michi@gmail.com
Requires-Python: >=3.9
Classifier: Intended Audience :: Developers
Classifier: Intended Audience :: Science/Research
Classifier: License :: OSI Approved :: MIT License
Classifier: Programming Language :: Python :: 3
Classifier: Programming Language :: Python :: 3.9
Classifier: Programming Language :: Python :: 3.10
Classifier: Programming Language :: Python :: 3.11
Classifier: Programming Language :: Python :: 3.12
Classifier: Programming Language :: Python :: 3.13
Classifier: Topic :: Scientific/Engineering
Classifier: Topic :: Software Development :: Libraries :: Python Modules
Classifier: Topic :: System :: Distributed Computing
Provides-Extra: viz
Requires-Dist: click (>=8.1.3,<9.0.0)
Requires-Dist: matplotlib (>=3.7.1,<4.0.0) ; extra == "viz"
Requires-Dist: mpi4py (>=3.1.6)
Requires-Dist: numba (>=0.57.0)
Requires-Dist: numpy (>1.20)
Project-URL: Documentation, https://argonnecpac.github.io/MPIPartition
Project-URL: Homepage, https://github.com/ArgonneCPAC/MPIPartition
Project-URL: Repository, https://github.com/ArgonneCPAC/MPIPartition
